{ 
    "type":"FeatureCollection",
    "name":"RLI Head Office",
    "crs":{ 
        "type":"name",
        "properties":{ 
            "name":"urn:ogc:def:crs:OGC:1.3:CRS84"
        }
    },
    "features":[ 
        { 
            "type":"Feature",
            "properties":{ 
                "Name":"RLI Head Office",
                "description":"RLI Education is the home base for our Institute's Centralized Finance Team, as well as:<br>-  our sister organization, the Métis Education Foundation<br>- K-12 Métis Education",
                "icon": "Head Office.png"
            },
            "geometry":{ 
                "type":"Point",
                "coordinates":[ 
                    -113.4879,
                    53.542158
                ]
            }
        }
    ]
}